epycom/__init__.py
epycom/artifact_detection/__init__.py
epycom/artifact_detection/powerline_noise.py
epycom/artifact_detection/saturation.py
epycom/bivariate/__init__.py
epycom/bivariate/coherence.py
epycom/bivariate/linear_correlation.py
epycom/bivariate/phase_consistency.py
epycom/bivariate/phase_lag_index.py
epycom/bivariate/phase_synchrony.py
epycom/bivariate/relative_entropy.py
epycom/bivariate/selection_entropy.py
epycom/bivariate/spectra_multiplication.py
epycom/event_detection/__init__.py
epycom/event_detection/hfo/__init__.py
epycom/event_detection/hfo/cs_detector.py
epycom/event_detection/hfo/hilbert_detector.py
epycom/event_detection/hfo/ll_detector.py
epycom/event_detection/hfo/nicolas_detector.py
epycom/event_detection/hfo/rms_detector.py
epycom/event_detection/spike/__init__.py
epycom/event_detection/spike/barkmeier_detector.py
epycom/event_detection/spike/janca_detector.py
epycom/event_detection/ufo/__init__.py
epycom/event_detection/ufo/ufo_detector.py
epycom/simulation/__init__.py
epycom/simulation/create_simulated.py
epycom/univariate/__init__.py
epycom/univariate/approximate_entropy.py
epycom/univariate/autoregressive_residual_modulation.py
epycom/univariate/fractal_dimension.py
epycom/univariate/hjorth_complexity.py
epycom/univariate/hjorth_mobility.py
epycom/univariate/low_f_marker.py
epycom/univariate/lyapunov_exponent.py
epycom/univariate/mean_vector_length.py
epycom/univariate/modulation_index.py
epycom/univariate/multiscale_entropy.py
epycom/univariate/phase_locking_value.py
epycom/univariate/power_spectral_entropy.py
epycom/univariate/sample_entropy.py
epycom/univariate/shannon_entropy.py
epycom/univariate/signal_stats.py
epycom/utils/__init__.py
epycom/utils/data_operations.py
epycom/utils/method.py
epycom/utils/signal_transforms.py
epycom/utils/thresholds.py
epycom/utils/tools.py
epycom/validation/__init__.py
epycom/validation/feature_evaluation.py
epycom/validation/precision_recall.py
epycom/validation/util.py
epycom-0.3.dist-info/licenses/LICENSE.txt
epycom-0.3.dist-info/METADATA
epycom-0.3.dist-info/WHEEL
epycom-0.3.dist-info/top_level.txt
epycom-0.3.dist-info/RECORD
