Metadata-Version: 2.4
Name: epycom
Version: 0.3
Summary: Package for EEG data processing and analysis
Home-page: 
Author: FNUSA-ICRC, BME
Author-email: jan.cimbalnik@fnusa.cz, jan.cimbalnik@mayo.edu
License: BSD 3.0
Keywords: EEG epilepsy signal processing
Classifier: Development Status :: 2 - Pre-Alpha
Classifier: Intended Audience :: Healthcare Industry
Classifier: Intended Audience :: Science/Research
Classifier: License :: OSI Approved :: BSD License
Classifier: Programming Language :: Python :: 3
Classifier: Operating System :: OS Independent
Classifier: Topic :: Scientific/Engineering :: Medical Science Apps.
License-File: LICENSE.txt
Requires-Dist: numpy<1.27
Requires-Dist: scipy
Requires-Dist: pandas
Requires-Dist: scikit-learn
Requires-Dist: numba
Provides-Extra: test
Requires-Dist: pytest; extra == "test"
Requires-Dist: pytest-benchmark; extra == "test"
Dynamic: author
Dynamic: author-email
Dynamic: classifier
Dynamic: keywords
Dynamic: license
Dynamic: license-file
Dynamic: provides-extra
Dynamic: requires-dist
Dynamic: summary
